classnotation/__init__.py
classnotation/dumper.py
classnotation/json_types.py
classnotation/loader.py
classnotation/py.typed
classnotation/typecheck_error.py
classnotation-1.5.dist-info/METADATA
classnotation-1.5.dist-info/WHEEL
classnotation-1.5.dist-info/top_level.txt
classnotation-1.5.dist-info/RECORD
